odoo/addons/purchase_reception_notify/README.rst
odoo/addons/purchase_reception_notify/__init__.py
odoo/addons/purchase_reception_notify/__manifest__.py
odoo/addons/purchase_reception_notify/hooks.py
odoo/addons/purchase_reception_notify/data/mail_data.xml
odoo/addons/purchase_reception_notify/i18n/es.po
odoo/addons/purchase_reception_notify/i18n/it.po
odoo/addons/purchase_reception_notify/i18n/pt_BR.po
odoo/addons/purchase_reception_notify/i18n/purchase_reception_notify.pot
odoo/addons/purchase_reception_notify/i18n/zh_CN.po
odoo/addons/purchase_reception_notify/models/__init__.py
odoo/addons/purchase_reception_notify/models/stock_picking.py
odoo/addons/purchase_reception_notify/readme/CONTRIBUTORS.md
odoo/addons/purchase_reception_notify/readme/DESCRIPTION.md
odoo/addons/purchase_reception_notify/readme/USAGE.md
odoo/addons/purchase_reception_notify/static/description/icon.png
odoo/addons/purchase_reception_notify/static/description/index.html
odoo/addons/purchase_reception_notify/tests/__init__.py
odoo/addons/purchase_reception_notify/tests/test_purchase_reception_notify.py
odoo_addon_purchase_reception_notify-18.0.1.0.1.3.dist-info/METADATA
odoo_addon_purchase_reception_notify-18.0.1.0.1.3.dist-info/WHEEL
odoo_addon_purchase_reception_notify-18.0.1.0.1.3.dist-info/top_level.txt
odoo_addon_purchase_reception_notify-18.0.1.0.1.3.dist-info/RECORD
